api/__init__.py
api/gpt4.py
api/handlers/__init__.py
api/handlers/animation.py
api/handlers/banner.py
api/handlers/exceptions.py
api/handlers/utils.py
api/modules/__init__.py
api/modules/chat.py
api/modules/design.py
api/modules/login.py
api_gpt4-1.0.7.dist-info/LICENSE
api_gpt4-1.0.7.dist-info/METADATA
api_gpt4-1.0.7.dist-info/WHEEL
api_gpt4-1.0.7.dist-info/top_level.txt
api_gpt4-1.0.7.dist-info/RECORD
