Metadata-Version: 2.1
Name: api-gpt4
Version: 1.0.7
Summary: The GPT-4 API is an interface for interacting with the powerful GPT-4 language model. It allows you to generate natural language text, perform question-answering tasks, and more. Whether you're building chatbots, content generators, or creative writing tools, GPT-4 has got you covered!
Author: Anupam Maurya
Author-email: anupammaurya981@gmail.com
License: MIT
Classifier: Development Status :: 3 - Alpha
Classifier: Intended Audience :: Developers
Classifier: Topic :: Software Development :: Build Tools
Classifier: Programming Language :: Python :: 3.11
Requires-Python: >=3.11
License-File: LICENSE
Requires-Dist: selenium ==4.18.1
Requires-Dist: beautifulsoup4 ==4.12.2
Requires-Dist: colorama ==0.4.6
